mishkal/__init__.py
mishkal/tashkeel.py
mishkal/tashkeel_const.py
mishkal/unknown_const.py
mishkal/unknown_tashkeel.py
mishkal/unkown.py
mishkal/unkown_const.py
mishkal/unkown_tashkeel.py
mishkal-0.4.dist-info/METADATA
mishkal-0.4.dist-info/RECORD
mishkal-0.4.dist-info/WHEEL
mishkal-0.4.dist-info/top_level.txt
