Metadata-Version: 2.1
Name: mishkal
Version: 0.4
Summary: Mishkal: Arabic text diacritization library for Python
Home-page: http://mishkal.sourceforge.net/
Author: Taha Zerrouki
Author-email: taha.zerrouki@gmail.com
License: GPL
Platform: UNKNOWN
Classifier: Development Status :: 5 - Production/Stable
Classifier: Intended Audience :: End Users/Desktop
Classifier: Operating System :: OS Independent
Classifier: Programming Language :: Python
Requires-Dist: libqutrub (>=1.0)
Requires-Dist: naftawayh (>=0.2)
Requires-Dist: pyarabic (>=0.6.2)
Requires-Dist: tashaphyne (>=0.3.1)
Requires-Dist: arramooz-pysqlite (>=0.1)
Requires-Dist: qalsadi (>=0.2)
Requires-Dist: mysam-tagmanager (>=0.1)
Requires-Dist: alyahmor (>=0.1)
Requires-Dist: asmai (>=0.1)
Requires-Dist: sylajone (>=0.1)
Requires-Dist: maskouk-pysqlite (>=0.1)
Requires-Dist: pickledb (>=0.9.0)
